eth_mnemonic_to_key/__init__.py
eth_mnemonic_to_key/converter.py
eth_mnemonic_to_key-0.1.dist-info/METADATA
eth_mnemonic_to_key-0.1.dist-info/WHEEL
eth_mnemonic_to_key-0.1.dist-info/top_level.txt
eth_mnemonic_to_key-0.1.dist-info/RECORD
