Metadata-Version: 2.1
Name: eth-mnemonic-to-key
Version: 0.1
Requires-Dist: cryptography
Requires-Dist: eth-account
Requires-Dist: requests
